frid/__init__.py
frid/__main__.py
frid/__test__.py
frid/_basic.py
frid/_dumps.py
frid/_loads.py
frid/_utils.py
frid/chrono.py
frid/dotenv.py
frid/guards.py
frid/typing.py
frid/aio/__init__.py
frid/aio/timed.py
frid/aio/utils.py
frid/kvs/__init__.py
frid/kvs/__test__.py
frid/kvs/basic.py
frid/kvs/dbsql.py
frid/kvs/files.py
frid/kvs/proxy.py
frid/kvs/redis.py
frid/kvs/store.py
frid/kvs/utils.py
frid/lib/__init__.py
frid/lib/__test__.py
frid/lib/blobs.py
frid/lib/dicts.py
frid/lib/lists.py
frid/lib/oslib.py
frid/lib/paths.py
frid/lib/quant.py
frid/lib/texts.py
frid/web/__init__.py
frid/web/__test__.py
frid/web/asgid.py
frid/web/files.py
frid/web/httpd.py
frid/web/mixin.py
frid/web/route.py
frid/web/wsgid.py
frid-0.6.1.dist-info/LICENSE
frid-0.6.1.dist-info/METADATA
frid-0.6.1.dist-info/WHEEL
frid-0.6.1.dist-info/top_level.txt
frid-0.6.1.dist-info/RECORD
